[
	{
		"__TYPE__": "SharedSliceContent",
		"variation": "default",
		"primary": {
			"text": {
				"__TYPE__": "StructuredTextContent",
				"value": [
					{
						"type": "paragraph",
						"content": {
							"text": "Esse aute consectetur ea exercitation tempor ut. Laboris velit tempor qui ut incididunt consectetur exercitation nostrud magna. Do nisi mollit culpa et esse do occaecat in enim."
						}
					}
				]
			},
			"image": {
				"__TYPE__": "ImageContent",
				"origin": {
					"id": "main",
					"url": "https://images.unsplash.com/photo-1525547719571-a2d4ac8945e2",
					"width": 3648,
					"height": 4560
				},
				"url": "https://images.unsplash.com/photo-1525547719571-a2d4ac8945e2",
				"width": 3648,
				"height": 4560,
				"edit": {
					"zoom": 1,
					"crop": {
						"x": 0,
						"y": 0
					},
					"background": "transparent"
				},
				"thumbnails": {}
			},
			"adresa": {
				"__TYPE__": "StructuredTextContent",
				"value": [
					{
						"type": "paragraph",
						"content": {
							"text": "In dolore sint culpa."
						}
					}
				]
			},
			"text_2": {
				"__TYPE__": "StructuredTextContent",
				"value": [
					{
						"type": "paragraph",
						"content": {
							"text": "Nulla voluptate laboris consequat laboris ut consequat occaecat occaecat id et incididunt exercitation non culpa."
						}
					}
				]
			}
		},
		"items": []
	}
]